slovnet/__init__.py
slovnet/api.py
slovnet/batch.py
slovnet/bert.py
slovnet/bio.py
slovnet/board.py
slovnet/chop.py
slovnet/conll.py
slovnet/const.py
slovnet/io.py
slovnet/log.py
slovnet/loss.py
slovnet/markup.py
slovnet/mask.py
slovnet/pad.py
slovnet/record.py
slovnet/s3.py
slovnet/score.py
slovnet/sent.py
slovnet/shape.py
slovnet/span.py
slovnet/tar.py
slovnet/token.py
slovnet/visitor.py
slovnet/vocab.py
slovnet/encoders/__init__.py
slovnet/encoders/bert.py
slovnet/encoders/buffer.py
slovnet/encoders/common.py
slovnet/encoders/syntax.py
slovnet/encoders/tag.py
slovnet/exec/__init__.py
slovnet/exec/encoders.py
slovnet/exec/infer.py
slovnet/exec/mask.py
slovnet/exec/model.py
slovnet/exec/pack.py
slovnet/exec/pad.py
slovnet/infer/__init__.py
slovnet/infer/base.py
slovnet/infer/bert.py
slovnet/infer/syntax.py
slovnet/infer/tag.py
slovnet/model/__init__.py
slovnet/model/base.py
slovnet/model/bert.py
slovnet/model/cnn.py
slovnet/model/crf.py
slovnet/model/emb.py
slovnet/model/exec.py
slovnet/model/state.py
slovnet/model/syntax.py
slovnet/model/tag.py
slovnet-0.6.0.dist-info/LICENSE
slovnet-0.6.0.dist-info/METADATA
slovnet-0.6.0.dist-info/WHEEL
slovnet-0.6.0.dist-info/top_level.txt
slovnet-0.6.0.dist-info/RECORD
