Metadata-Version: 2.1
Name: slovnet
Version: 0.6.0
Summary: Deep-learning based NLP modeling for Russian language
Home-page: https://github.com/natasha/slovnet
Author: Alexander Kukushkin
Author-email: alex@alexkuk.ru
License: MIT
Keywords: nlp,deeplearning,russian
Classifier: License :: OSI Approved :: MIT License
Classifier: Programming Language :: Python :: 3
Classifier: Topic :: Scientific/Engineering :: Artificial Intelligence
License-File: LICENSE
